dahi/knowledgebase.py
dahi/example2.py
dahi/storages.py
dahi/statement.py
dahi/__init__.py
dahi/contexts.py
dahi/nlu.py
dahi/context.py
dahi/bots.py
dahi/documents.py
dahi/document.py
dahi/bot.py
dahi/matchers/tfidfMatcher.pyc
dahi/matchers/__init__.pyc
dahi/matchers/__init__.py
dahi/matchers/abstracts.py
dahi/matchers/abstracts.pyc
dahi/matchers/tfidfMatcher.py
bot_dahi-0.1.13.dist-info/metadata.json
bot_dahi-0.1.13.dist-info/WHEEL
bot_dahi-0.1.13.dist-info/top_level.txt
bot_dahi-0.1.13.dist-info/METADATA
bot_dahi-0.1.13.dist-info/DESCRIPTION.rst
bot_dahi-0.1.13.dist-info/RECORD
