Metadata-Version: 2.0
Name: bot-dahi
Version: 0.1.13
Summary: question answer bot
Home-page: https://github.com/muatik/dahi
Author: Mustafa Atik
Author-email: muatik@gmail.com
License: The MIT License (MIT)
